ui_finder/__init__.py
ui_finder/__main__.py
ui_finder/__version__.py
ui_finder/adb_handler.py
ui_finder/adb_utils.py
ui_finder/clear_data.py
ui_finder/dep_check.py
ui_finder/device_detector.py
ui_finder/device_utils.py
ui_finder/main.py
ui_finder/startup_check.py
ui_finder/viewer copy.py
ui_finder/viewer.py
ui_finder-2.0.1.dist-info/LICENSE
ui_finder-2.0.1.dist-info/METADATA
ui_finder-2.0.1.dist-info/WHEEL
ui_finder-2.0.1.dist-info/entry_points.txt
ui_finder-2.0.1.dist-info/top_level.txt
ui_finder-2.0.1.dist-info/RECORD
