Metadata-Version: 2.1
Name: ui_finder
Version: 2.0.1
Summary: Android UI elements inspector for automating UI testing and development.
Home-page: https://github.com/kdiitg/ui_finder
Author: Kuldeep Singh
Author-email: kdiitg@gmail.com
License: MIT
Project-URL: Documentation, https://github.com/kdiitg/{module_name}
Project-URL: Source, https://github.com/kdiitg/{module_name}
Project-URL: Bug Tracker, https://github.com/kdiitg/{module_name}/issues
Keywords: android,ui,inspector,automation,testing,development,adb
Classifier: Programming Language :: Python :: 3
Classifier: License :: OSI Approved :: MIT License
Classifier: Operating System :: OS Independent
Classifier: Topic :: Internet :: File Transfer Protocol (FTP)
Classifier: Topic :: Utilities
Requires-Python: >=3.7
License-File: LICENSE
Requires-Dist: Pillow ~=11.2.1
Requires-Dist: qrcode ~=8.2
Requires-Dist: requests ~=2.32.4
